{

   "service1" : [
        {
            "podA" :[
                {
                    "sender" : "/register",
                    "receiver" : "http://localhost:8081",
                    "auth_required" : "false"
                } 
            ],
            "podB" :[
                {
                    "sender" : "/register",
                    "receiver" : "http://localhost:8083",
                    "auth_required" : "false"
                } 
            ]
        }

    ],
    "service2" : [
        {

            "sender" : "/auth",
            "receiver" : "http://localhost:8002/user",
            "auth_required" : "false"

        }
  
    ],
    "service3" : [
        {
   
            "sender" : "/auth",
            "receiver" : "http://localhost:8002/user",
            "auth_required" : "false"

        }
  
    ]
    

}